</alberghi>
    <albergo>
        <comune>"DUINO-AURISINA"</comune>
        <provincia>"TRIESTE"</provincia>
        <tipo>"Alberghi"</tipo>
        <categoria>"1 Stella *"</categoria>
        <tipologia>"Casa principale"</tipologia>
        <denominazione>"DAMA BIANCA"</denominazione>
        <localita>"-"</localita>
        <frazione>"DUINO AURISINA"</frazione>
        <indirizzo>"DUINO, 61/C"</indirizzo>
        <cap>"34011"</cap>
        <telefono>"040  208137 - 208470"</telefono>
        <cellulare>"-"</cellulare>
        <fax>"040  208258"</fax>
        <indirizzo_posta_elettronica>"info@alladamabianca.com"</indirizzo_posta_elettronica>
        <sito_internet>"http://www.alladamabianca.com"</sito_internet>
        <camere>7</camere>
        <posti_letto>14</posti_letto>
        <bagni>7</bagni>
        <periodo_apertura>"01.I - 31.XII"</periodo_apertura>
        <centro_abitato>"NO"</centro_abitato>
        <zona_aereoporto>"NO"</zona_aereoporto>
        <zona_stazione_ffss>"NO"</zona_stazione_ffss>
        <in_campagna>"NO"</in_campagna>
        <sul_mare>"SI"</sul_mare>
        <sul_lago>"NO"</sul_lago>
        <sul_fiume>"NO"</sul_fiume>
        <zona_impianti_risalita>"NO"</zona_impianti_risalita>
        <interesse_storico>"NO"</interesse_storico>
        <villa>"NO"</villa>
        <castello>"NO"</castello>
        <accessibile>"Non accessibile"</accessibile>
        <ascensore>"NO"</ascensore>
        <ristorante>"SI"</ristorante>
        <ristorante_convenzionato>"NO"</ristorante_convenzionato>
        <ristorante_vegetariano>"NO"</ristorante_vegetariano>
        <tavola_calda>"NO"</tavola_calda>
        <bar>"SI"</bar>
        <giochi_bambini>"NO"</giochi_bambini>
        <sala_lettura>"NO"</sala_lettura>
        <sala_tv>"NO"</sala_tv>
        <sala_tv_comune>"NO"</sala_tv_comune>
        <parco_giardino>"NO"</parco_giardino>
        <animali_domestici>"NO"</animali_domestici>
        <servizio_congressi>"NO"</servizio_congressi>
        <servizio_congressi_min>0</servizio_congressi_min>
        <servizio_congressi_max>0</servizio_congressi_max>
        <accettazione_gruppi>"NO"</accettazione_gruppi>
        <accesso_mezzi_pubblici>"NO"</accesso_mezzi_pubblici>
        <accesso_mezzi_privati>"NO"</accesso_mezzi_privati>
        <parcheggio_non_custodito>"SI"</parcheggio_non_custodito>
        <garage>"NO"</garage>
        <trasporto_clienti>"NO"</trasporto_clienti>
        <pulizia_calzature>"NO"</pulizia_calzature>
        <lavatura_stiratura>"NO"</lavatura_stiratura>
        <baby_sitting>"NO"</baby_sitting>
        <altri_impianti_servizi>"-"</altri_impianti_servizi>
        <custodia_valori_cassaforte>"NO"</custodia_valori_cassaforte>
        <custodia_valori_cassetta_sicurezza>"NO"</custodia_valori_cassetta_sicurezza>
        <vasca_idromassaggio>"NO"</vasca_idromassaggio>
        <doccia_idromassaggio>"NO"</doccia_idromassaggio>
        <doccia_sauna>"NO"</doccia_sauna>
        <sauna_privata>"NO"</sauna_privata>
        <palestra>"NO"</palestra>
        <impianti_termali>"NO"</impianti_termali>
        <centro_benessere>"NO"</centro_benessere>
        <spiaggia_riservata>"SI"</spiaggia_riservata>
        <discoteca>"NO"</discoteca>
        <postazioni_internet>"NO"</postazioni_internet>
        <tv_satellitare>"NO"</tv_satellitare>
        <aria_condizionata>"NO"</aria_condizionata>
        <lingua_inglese>"SI"</lingua_inglese>
        <lingua_francese>"NO"</lingua_francese>
        <lingua_spagnola>"NO"</lingua_spagnola>
        <lingua_tedesca>"SI"</lingua_tedesca>
        <altre_lingue>"SLOVENO, CROATO"</altre_lingue>
        <tennis>"NO"</tennis>
        <piscina_coperta>"NO"</piscina_coperta>
        <piscina_scoperta>"NO"</piscina_scoperta>
        <golf>"NO"</golf>
        <equitazione>"NO"</equitazione>
        <vela>"NO"</vela>
        <windsurf>"NO"</windsurf>
        <sub>"NO"</sub>
        <ricarica_bombole_sub>"NO"</ricarica_bombole_sub>
        <sci_nautico>"NO"</sci_nautico>
        <sci_montano>"NO"</sci_montano>
        <ormeggio>"NO"</ormeggio>
        <altri_impianti_sportivi>"-"</altri_impianti_sportivi>
        <american_express>"SI"</american_express>
        <carta_si>"SI"</carta_si>
        <diners>"SI"</diners>
        <eurocard_mastercard>"SI"</eurocard_mastercard>
        <jcb>"SI"</jcb>
        <visa>"SI"</visa>
        <bancomat_pos>"SI"</bancomat_pos>
        <cirrus>"SI"</cirrus>
        <maestro>"SI"</maestro>
        <altre_carte_credito>"-"</altre_carte_credito>
        <codice_esercizio>"210"</codice_esercizio>
    </albergo>

    <albergo>
        <comune>"MUGGIA"</comune>
        <provincia>"TRIESTE"</provincia>
        <tipo>"Alberghi"</tipo>
        <categoria>"4 Stelle ****"</categoria>
        <tipologia>"Casa principale"</tipologia>
        <denominazione>"HOTEL SAN ROCCO"</denominazione>
        <localita>"-"</localita>
        <frazione>"-"</frazione>
        <indirizzo>"STRADA PER LAZZARETTO, 2"</indirizzo>
        <cap>"34015"</cap>
        <telefono>"040 330100"</telefono>
        <cellulare>"-"</cellulare>
        <fax>"040 271867"</fax>
        <indirizzo_posta_elettronica>"hotelsanrocco@gmail.com"</indirizzo_posta_elettronica>
        <sito_internet>"http://www.hotelsanrocco.com"</sito_internet>
        <camere>64</camere>
        <posti_letto>172</posti_letto>
        <bagni>64</bagni>
        <periodo_apertura>"01.I - 31.XII"</periodo_apertura>
        <centro_abitato>"NO"</centro_abitato>
        <zona_aereoporto>"NO"</zona_aereoporto>
        <zona_stazione_ffss>"NO"</zona_stazione_ffss>
        <in_campagna>"NO"</in_campagna>
        <sul_mare>"SI"</sul_mare>
        <sul_lago>"NO"</sul_lago>
        <sul_fiume>"NO"</sul_fiume>
        <zona_impianti_risalita>"NO"</zona_impianti_risalita>
        <interesse_storico>"NO"</interesse_storico>
        <villa>"NO"</villa>
        <castello>"NO"</castello>
        <accessibile>"Eccellente"</accessibile>
        <ascensore>"SI"</ascensore>
        <ristorante>"SI"</ristorante>
        <ristorante_convenzionato>"SI"</ristorante_convenzionato>
        <ristorante_vegetariano>"NO"</ristorante_vegetariano>
        <tavola_calda>"NO"</tavola_calda>
        <bar>"SI"</bar>
        <giochi_bambini>"NO"</giochi_bambini>
        <sala_lettura>"NO"</sala_lettura>
        <sala_tv>"NO"</sala_tv>
        <sala_tv_comune>"SI"</sala_tv_comune>
        <parco_giardino>"NO"</parco_giardino>
        <animali_domestici>"SI"</animali_domestici>
        <servizio_congressi>"NO"</servizio_congressi>
        <servizio_congressi_min>0</servizio_congressi_min>
        <servizio_congressi_max>0</servizio_congressi_max>
        <accettazione_gruppi>"SI"</accettazione_gruppi>
        <accesso_mezzi_pubblici>"SI"</accesso_mezzi_pubblici>
        <accesso_mezzi_privati>"SI"</accesso_mezzi_privati>
        <parcheggio_non_custodito>"NO"</parcheggio_non_custodito>
        <garage>"SI"</garage>
        <trasporto_clienti>"NO"</trasporto_clienti>
        <pulizia_calzature>"NO"</pulizia_calzature>
        <lavatura_stiratura>"SI"</lavatura_stiratura>
        <baby_sitting>"NO"</baby_sitting>
        <altri_impianti_servizi>"-"</altri_impianti_servizi>
        <custodia_valori_cassaforte>"NO"</custodia_valori_cassaforte>
        <custodia_valori_cassetta_sicurezza>"NO"</custodia_valori_cassetta_sicurezza>
        <vasca_idromassaggio>"NO"</vasca_idromassaggio>
        <doccia_idromassaggio>"NO"</doccia_idromassaggio>
        <doccia_sauna>"NO"</doccia_sauna>
        <sauna_privata>"NO"</sauna_privata>
        <palestra>"NO"</palestra>
        <impianti_termali>"NO"</impianti_termali>
        <centro_benessere>"NO"</centro_benessere>
        <spiaggia_riservata>"NO"</spiaggia_riservata>
        <discoteca>"NO"</discoteca>
        <postazioni_internet>"NO"</postazioni_internet>
        <tv_satellitare>"SI"</tv_satellitare>
        <aria_condizionata>"SI"</aria_condizionata>
        <lingua_inglese>"SI"</lingua_inglese>
        <lingua_francese>"SI"</lingua_francese>
        <lingua_spagnola>"NO"</lingua_spagnola>
        <lingua_tedesca>"SI"</lingua_tedesca>
        <altre_lingue>"-"</altre_lingue>
        <tennis>"NO"</tennis>
        <piscina_coperta>"NO"</piscina_coperta>
        <piscina_scoperta>"NO"</piscina_scoperta>
        <golf>"NO"</golf>
        <equitazione>"NO"</equitazione>
        <vela>"NO"</vela>
        <windsurf>"NO"</windsurf>
        <sub>"NO"</sub>
        <ricarica_bombole_sub>"NO"</ricarica_bombole_sub>
        <sci_nautico>"NO"</sci_nautico>
        <sci_montano>"NO"</sci_montano>
        <ormeggio>"NO"</ormeggio>
        <altri_impianti_sportivi>"-"</altri_impianti_sportivi>
        <american_express>"SI"</american_express>
        <carta_si>"SI"</carta_si>
        <diners>"SI"</diners>
        <eurocard_mastercard>"SI"</eurocard_mastercard>
        <jcb>"SI"</jcb>
        <visa>"SI"</visa>
        <bancomat_pos>"SI"</bancomat_pos>
        <cirrus>"SI"</cirrus>
        <maestro>"SI"</maestro>
        <altre_carte_credito>"-"</altre_carte_credito>
        <codice_esercizio>"59640"</codice_esercizio>
    </albergo>

    <albergo>
        <comune>"TRIESTE"</comune>
        <provincia>"TRIESTE"</provincia>
        <tipo>"Alberghi"</tipo>
        <categoria>"5 Stelle *****"</categoria>
        <tipologia>"Casa principale"</tipologia>
        <denominazione>"HOTEL GREIF MARIA THERESIA"</denominazione>
        <localita>"BARCOLA"</localita>
        <frazione>"-"</frazione>
        <indirizzo>"VIALE MIRAMARE, 109"</indirizzo>
        <cap>"34136"</cap>
        <telefono>"040  410115"</telefono>
        <cellulare>"-"</cellulare>
        <fax>"040  413053"</fax>
        <indirizzo_posta_elettronica>"greifts@tin.it"</indirizzo_posta_elettronica>
        <sito_internet>"http://www.greifgroup.net"</sito_internet>
        <camere>33</camere>
        <posti_letto>66</posti_letto>
        <bagni>33</bagni>
        <periodo_apertura>"01.I - 31.XII"</periodo_apertura>
        <centro_abitato>"NO"</centro_abitato>
        <zona_aereoporto>"NO"</zona_aereoporto>
        <zona_stazione_ffss>"NO"</zona_stazione_ffss>
        <in_campagna>"NO"</in_campagna>
        <sul_mare>"SI"</sul_mare>
        <sul_lago>"NO"</sul_lago>
        <sul_fiume>"NO"</sul_fiume>
        <zona_impianti_risalita>"NO"</zona_impianti_risalita>
        <interesse_storico>"NO"</interesse_storico>
        <villa>"SI"</villa>
        <castello>"NO"</castello>
        <accessibile>"Accessibile"</accessibile>
        <ascensore>"SI"</ascensore>
        <ristorante>"SI"</ristorante>
        <ristorante_convenzionato>"NO"</ristorante_convenzionato>
        <ristorante_vegetariano>"NO"</ristorante_vegetariano>
        <tavola_calda>"NO"</tavola_calda>
        <bar>"SI"</bar>
        <giochi_bambini>"NO"</giochi_bambini>
        <sala_lettura>"SI"</sala_lettura>
        <sala_tv>"SI"</sala_tv>
        <sala_tv_comune>"NO"</sala_tv_comune>
        <parco_giardino>"SI"</parco_giardino>
        <animali_domestici>"SI"</animali_domestici>
        <servizio_congressi>"SI"</servizio_congressi>
        <servizio_congressi_min>5</servizio_congressi_min>
        <servizio_congressi_max>110</servizio_congressi_max>
        <accettazione_gruppi>"SI"</accettazione_gruppi>
        <accesso_mezzi_pubblici>"NO"</accesso_mezzi_pubblici>
        <accesso_mezzi_privati>"SI"</accesso_mezzi_privati>
        <parcheggio_non_custodito>"SI"</parcheggio_non_custodito>
        <garage>"SI"</garage>
        <trasporto_clienti>"SI"</trasporto_clienti>
        <pulizia_calzature>"NO"</pulizia_calzature>
        <lavatura_stiratura>"SI"</lavatura_stiratura>
        <baby_sitting>"SI"</baby_sitting>
        <altri_impianti_servizi>"-"</altri_impianti_servizi>
        <custodia_valori_cassaforte>"NO"</custodia_valori_cassaforte>
        <custodia_valori_cassetta_sicurezza>"NO"</custodia_valori_cassetta_sicurezza>
        <vasca_idromassaggio>"SI"</vasca_idromassaggio>
        <doccia_idromassaggio>"NO"</doccia_idromassaggio>
        <doccia_sauna>"SI"</doccia_sauna>
        <sauna_privata>"NO"</sauna_privata>
        <palestra>"NO"</palestra>
        <impianti_termali>"NO"</impianti_termali>
        <centro_benessere>"SI"</centro_benessere>
        <spiaggia_riservata>"NO"</spiaggia_riservata>
        <discoteca>"NO"</discoteca>
        <postazioni_internet>"SI"</postazioni_internet>
        <tv_satellitare>"SI"</tv_satellitare>
        <aria_condizionata>"SI"</aria_condizionata>
        <lingua_inglese>"SI"</lingua_inglese>
        <lingua_francese>"NO"</lingua_francese>
        <lingua_spagnola>"NO"</lingua_spagnola>
        <lingua_tedesca>"SI"</lingua_tedesca>
        <altre_lingue>"CROATO"</altre_lingue>
        <tennis>"NO"</tennis>
        <piscina_coperta>"SI"</piscina_coperta>
        <piscina_scoperta>"NO"</piscina_scoperta>
        <golf>"NO"</golf>
        <equitazione>"NO"</equitazione>
        <vela>"NO"</vela>
        <windsurf>"NO"</windsurf>
        <sub>"NO"</sub>
        <ricarica_bombole_sub>"NO"</ricarica_bombole_sub>
        <sci_nautico>"NO"</sci_nautico>
        <sci_montano>"NO"</sci_montano>
        <ormeggio>"NO"</ormeggio>
        <altri_impianti_sportivi>"-"</altri_impianti_sportivi>
        <american_express>"SI"</american_express>
        <carta_si>"SI"</carta_si>
        <diners>"SI"</diners>
        <eurocard_mastercard>"SI"</eurocard_mastercard>
        <jcb>"NO"</jcb>
        <visa>"SI"</visa>
        <bancomat_pos>"SI"</bancomat_pos>
        <cirrus>"NO"</cirrus>
        <maestro>"SI"</maestro>
        <altre_carte_credito>"-"</altre_carte_credito>
        <codice_esercizio>"151"</codice_esercizio>
    </albergo>

    <albergo>
        <comune>"DUINO-AURISINA"</comune>
        <provincia>"TRIESTE"</provincia>
        <tipo>"Alberghi"</tipo>
        <categoria>"5 Stelle lusso *****"</categoria>
        <tipologia>"Casa principale"</tipologia>
        <denominazione>"HOTEL FALISIA, A LUXURY COLLECTION RESORT &amp; SPA"</denominazione>
        <localita>"SISTIANA"</localita>
        <frazione>"-"</frazione>
        <indirizzo>"-, 231/M"</indirizzo>
        <cap>"34011"</cap>
        <telefono>"040 9974444"</telefono>
        <cellulare>"-"</cellulare>
        <fax>"-"</fax>
        <indirizzo_posta_elettronica>"info@falisiaresort.com"</indirizzo_posta_elettronica>
        <sito_internet>"http://www.falisiaresort.com"</sito_internet>
        <camere>46</camere>
        <posti_letto>105</posti_letto>
        <bagni>46</bagni>
        <periodo_apertura>"01.I - 31.XII"</periodo_apertura>
        <centro_abitato>"NO"</centro_abitato>
        <zona_aereoporto>"NO"</zona_aereoporto>
        <zona_stazione_ffss>"NO"</zona_stazione_ffss>
        <in_campagna>"NO"</in_campagna>
        <sul_mare>"SI"</sul_mare>
        <sul_lago>"NO"</sul_lago>
        <sul_fiume>"NO"</sul_fiume>
        <zona_impianti_risalita>"NO"</zona_impianti_risalita>
        <interesse_storico>"NO"</interesse_storico>
        <villa>"NO"</villa>
        <castello>"NO"</castello>
        <accessibile>"Non censito"</accessibile>
        <ascensore>"SI"</ascensore>
        <ristorante>"SI"</ristorante>
        <ristorante_convenzionato>"NO"</ristorante_convenzionato>
        <ristorante_vegetariano>"SI"</ristorante_vegetariano>
        <tavola_calda>"NO"</tavola_calda>
        <bar>"SI"</bar>
        <giochi_bambini>"NO"</giochi_bambini>
        <sala_lettura>"SI"</sala_lettura>
        <sala_tv>"NO"</sala_tv>
        <sala_tv_comune>"SI"</sala_tv_comune>
        <parco_giardino>"NO"</parco_giardino>
        <animali_domestici>"SI"</animali_domestici>
        <servizio_congressi>"SI"</servizio_congressi>
        <servizio_congressi_min>0</servizio_congressi_min>
        <servizio_congressi_max>0</servizio_congressi_max>
        <accettazione_gruppi>"SI"</accettazione_gruppi>
        <accesso_mezzi_pubblici>"NO"</accesso_mezzi_pubblici>
        <accesso_mezzi_privati>"SI"</accesso_mezzi_privati>
        <parcheggio_non_custodito>"NO"</parcheggio_non_custodito>
        <garage>"SI"</garage>
        <trasporto_clienti>"SI"</trasporto_clienti>
        <pulizia_calzature>"SI"</pulizia_calzature>
        <lavatura_stiratura>"SI"</lavatura_stiratura>
        <baby_sitting>"SI"</baby_sitting>
        <altri_impianti_servizi>"-"</altri_impianti_servizi>
        <custodia_valori_cassaforte>"SI"</custodia_valori_cassaforte>
        <custodia_valori_cassetta_sicurezza>"NO"</custodia_valori_cassetta_sicurezza>
        <vasca_idromassaggio>"SI"</vasca_idromassaggio>
        <doccia_idromassaggio>"NO"</doccia_idromassaggio>
        <doccia_sauna>"SI"</doccia_sauna>
        <sauna_privata>"NO"</sauna_privata>
        <palestra>"SI"</palestra>
        <impianti_termali>"NO"</impianti_termali>
        <centro_benessere>"SI"</centro_benessere>
        <spiaggia_riservata>"SI"</spiaggia_riservata>
        <discoteca>"NO"</discoteca>
        <postazioni_internet>"SI"</postazioni_internet>
        <tv_satellitare>"SI"</tv_satellitare>
        <aria_condizionata>"SI"</aria_condizionata>
        <lingua_inglese>"SI"</lingua_inglese>
        <lingua_francese>"SI"</lingua_francese>
        <lingua_spagnola>"SI"</lingua_spagnola>
        <lingua_tedesca>"SI"</lingua_tedesca>
        <altre_lingue>"-"</altre_lingue>
        <tennis>"NO"</tennis>
        <piscina_coperta>"NO"</piscina_coperta>
        <piscina_scoperta>"SI"</piscina_scoperta>
        <golf>"NO"</golf>
        <equitazione>"NO"</equitazione>
        <vela>"SI"</vela>
        <windsurf>"SI"</windsurf>
        <sub>"SI"</sub>
        <ricarica_bombole_sub>"NO"</ricarica_bombole_sub>
        <sci_nautico>"NO"</sci_nautico>
        <sci_montano>"NO"</sci_montano>
        <ormeggio>"SI"</ormeggio>
        <altri_impianti_sportivi>"-"</altri_impianti_sportivi>
        <american_express>"SI"</american_express>
        <carta_si>"SI"</carta_si>
        <diners>"NO"</diners>
        <eurocard_mastercard>"SI"</eurocard_mastercard>
        <jcb>"NO"</jcb>
        <visa>"SI"</visa>
        <bancomat_pos>"SI"</bancomat_pos>
        <cirrus>"SI"</cirrus>
        <maestro>"SI"</maestro>
        <altre_carte_credito>"-"</altre_carte_credito>
        <codice_esercizio>"64641"</codice_esercizio>
    </albergo>
</alberghi>